ciberedev/__init__.py
ciberedev/__main__.py
ciberedev/client.py
ciberedev/errors.py
ciberedev/file.py
ciberedev/http.py
ciberedev/searching.py
ciberedev/types/image.py
ciberedev/types/random.py
ciberedev/types/screenshot.py
ciberedev/types/searching.py
ciberedev.py-0.5.2.dist-info/LICENSE
ciberedev.py-0.5.2.dist-info/METADATA
ciberedev.py-0.5.2.dist-info/WHEEL
ciberedev.py-0.5.2.dist-info/top_level.txt
ciberedev.py-0.5.2.dist-info/RECORD
