Metadata-Version: 2.1
Name: ciberedev.py
Version: 0.5.2
Summary: A basic wrapper cibere.dev
Home-page: https://github.com/cibere/ciberedev.py
Author: cibere
Author-email: cibere.dev@gmail.com
License: MIT
Project-URL: Code, https://github.com/cibere/ciberedev.py
Project-URL: Issue tracker, https://github.com/cibere/ciberedev.py/issues
Project-URL: Discord/Support Server, https://discord.gg/2MRrJvP42N
Requires-Python: >=3.8
License-File: LICENSE
Requires-Dist: aiohttp
